param/__init__.py
param/_version.py
param/ipython.py
param/numbergen.py
param/parameterized.py
param2-2.0.0.dev2.dist-info/DESCRIPTION.rst
param2-2.0.0.dev2.dist-info/METADATA
param2-2.0.0.dev2.dist-info/RECORD
param2-2.0.0.dev2.dist-info/WHEEL
param2-2.0.0.dev2.dist-info/metadata.json
param2-2.0.0.dev2.dist-info/top_level.txt
